stitches/__init__.py
stitches/_grass.py
stitches/cli.py
stitches/core.py
stitches/session.py
stitches/tasks.py
stitches_gis-1.0.0.dist-info/COPYING
stitches_gis-1.0.0.dist-info/METADATA
stitches_gis-1.0.0.dist-info/WHEEL
stitches_gis-1.0.0.dist-info/entry_points.txt
stitches_gis-1.0.0.dist-info/top_level.txt
stitches_gis-1.0.0.dist-info/RECORD
