Metadata-Version: 2.1
Name: stitches-gis
Version: 1.0.0
Summary: A task runner for GRASS GIS
Home-page: https://github.com/davebrent/stitches
Author: Dave Poulter
Author-email: hello@davepoulter.net
License: GPLv3
Keywords: gis grass-gis task-runner
Platform: UNKNOWN
Classifier: Development Status :: 4 - Beta
Classifier: Environment :: Console
Classifier: Topic :: Scientific/Engineering :: GIS
Requires-Dist: colorful
Requires-Dist: docopt
Requires-Dist: jinja2
Requires-Dist: toml
Requires-Dist: wurlitzer
